posidrive/__init__.py
posidrive/gdrive.py
posidrive/util.py
posidrive-0.1.1.dist-info/LICENSE
posidrive-0.1.1.dist-info/METADATA
posidrive-0.1.1.dist-info/WHEEL
posidrive-0.1.1.dist-info/top_level.txt
posidrive-0.1.1.dist-info/RECORD
